{
  "_class": "shapeGroup",
  "booleanOperation": 0,
  "clippingMaskMode": 0,
  "do_objectID": "CCCBBEBE-3029-40B4-939C-F2FB02F8EBCB",
  "exportOptions": {
    "_class": "exportOptions",
    "do_objectID": "CB68D485-19B5-4B95-9EC4-B78D681CE0D7",
    "exportFormats": [
    ],
    "includedLayerIds": [
    ],
    "layerOptions": 0,
    "shouldTrim": false
  },
  "frame": {
    "_class": "rect",
    "constrainProportions": false,
    "do_objectID": "2E4169AF-D27A-41E5-BDD2-E9C67A566A02",
    "height": 1,
    "width": 360,
    "x": 0,
    "y": 383
  },
  "hasClickThrough": false,
  "hasClippingMask": false,
  "isFixedToViewport": false,
  "isFlippedHorizontal": false,
  "isFlippedVertical": false,
  "isLocked": false,
  "isVisible": true,
  "layerListExpandedType": 0,
  "layers": [
    {
      "class": "rectangle",
      "id": "1BA00BA4-9736-4E78-A326-86527E2FED6D"
    }
  ],
  "name": "Rectangle-path",
  "nameIsFixed": false,
  "resizingConstraint": 63,
  "resizingType": 0,
  "rotation": 0,
  "shouldBreakMaskChain": false,
  "style": {
    "_class": "style",
    "do_objectID": "AD5D260E-DE3B-45FF-A4A2-8D6C81C91695",
    "endMarkerType": 0,
    "fills": [
      {
        "_class": "fill",
        "color": {
          "_class": "color",
          "alpha": 1,
          "blue": 0.7098039215686275,
          "green": 0.3176470588235292,
          "red": 0.2470588235294118
        },
        "fillType": 0,
        "isEnabled": true,
        "noiseIndex": 0,
        "noiseIntensity": 0,
        "patternFillType": 0,
        "patternTileScale": 1
      }
    ],
    "miterLimit": 10,
    "startMarkerType": 0,
    "windingRule": 1
  },
  "windingRule": 1
}