{
  "_class": "shapePath",
  "booleanOperation": -1,
  "do_objectID": "E9B744D9-B6CD-460E-B4CC-BD31F1E75882",
  "edited": true,
  "exportOptions": {
    "_class": "exportOptions",
    "do_objectID": "BF1C7109-444C-4FE4-BDD3-10B5FD936D7C",
    "exportFormats": [
    ],
    "includedLayerIds": [
    ],
    "layerOptions": 0,
    "shouldTrim": false
  },
  "frame": {
    "_class": "rect",
    "constrainProportions": false,
    "do_objectID": "BC456F44-FDF0-4C3A-897C-3977822A6AEA",
    "height": 9,
    "width": 18,
    "x": 4,
    "y": 13
  },
  "isClosed": true,
  "isFixedToViewport": false,
  "isFlippedHorizontal": false,
  "isFlippedVertical": false,
  "isLocked": false,
  "isVisible": true,
  "layerListExpandedType": 0,
  "name": "Path",
  "nameIsFixed": false,
  "pointRadiusBehaviour": 1,
  "points": [
    {
      "_class": "curvePoint",
      "cornerRadius": 0,
      "curveFrom": "{1, 1}",
      "curveMode": 1,
      "curveTo": "{1, 1}",
      "hasCurveFrom": false,
      "hasCurveTo": false,
      "point": "{1, 1}"
    },
    {
      "_class": "curvePoint",
      "cornerRadius": 0,
      "curveFrom": "{0, 1}",
      "curveMode": 1,
      "curveTo": "{0, 1}",
      "hasCurveFrom": false,
      "hasCurveTo": false,
      "point": "{0, 1}"
    },
    {
      "_class": "curvePoint",
      "cornerRadius": 0,
      "curveFrom": "{0.73893805309734495, 0}",
      "curveMode": 1,
      "curveTo": "{0.73893805309734495, 0}",
      "hasCurveFrom": false,
      "hasCurveTo": false,
      "point": "{0.73893805309734495, 0}"
    },
    {
      "_class": "curvePoint",
      "cornerRadius": 0,
      "curveFrom": "{1, 0.51487414187643021}",
      "curveMode": 1,
      "curveTo": "{1, 0.51487414187643021}",
      "hasCurveFrom": false,
      "hasCurveTo": false,
      "point": "{1, 0.51487414187643021}"
    }
  ],
  "resizingConstraint": 63,
  "resizingType": 0,
  "rotation": 0,
  "shouldBreakMaskChain": false
}