{
  "_class": "shapePath",
  "booleanOperation": -1,
  "do_objectID": "3D55FC86-5DC9-4348-A4B3-A9B956AEE669",
  "edited": true,
  "exportOptions": {
    "_class": "exportOptions",
    "do_objectID": "EB7291E4-CA5B-4AC0-929C-D4427F004F97",
    "exportFormats": [
    ],
    "includedLayerIds": [
    ],
    "layerOptions": 0,
    "shouldTrim": false
  },
  "frame": {
    "_class": "rect",
    "constrainProportions": false,
    "do_objectID": "61E6EB64-8393-413C-A5E4-B1CCCDA033BE",
    "height": 3.999999999999989,
    "width": 5.999999999999989,
    "x": 0,
    "y": 0
  },
  "isClosed": true,
  "isFlippedHorizontal": false,
  "isFlippedVertical": false,
  "isLocked": false,
  "isVisible": true,
  "layerListExpandedType": 0,
  "name": "Path",
  "nameIsFixed": false,
  "pointRadiusBehaviour": 1,
  "points": [
    {
      "_class": "curvePoint",
      "cornerRadius": 0,
      "curveFrom": "{0.8571428571428571, 1}",
      "curveMode": 1,
      "curveTo": "{0.8571428571428571, 1}",
      "hasCurveFrom": false,
      "hasCurveTo": false,
      "point": "{0.8571428571428571, 1}"
    },
    {
      "_class": "curvePoint",
      "cornerRadius": 0,
      "curveFrom": "{0.8571428571428571, 0.10227272727272728}",
      "curveMode": 4,
      "curveTo": "{0.8571428571428571, 0.22727272727272727}",
      "hasCurveFrom": true,
      "hasCurveTo": false,
      "point": "{0.8571428571428571, 0.22727272727272727}"
    },
    {
      "_class": "curvePoint",
      "cornerRadius": 0,
      "curveFrom": "{1, 0}",
      "curveMode": 4,
      "curveTo": "{0.92142857142857137, 0}",
      "hasCurveFrom": false,
      "hasCurveTo": true,
      "point": "{1, 0}"
    },
    {
      "_class": "curvePoint",
      "cornerRadius": 0,
      "curveFrom": "{0.064285714285714279, 0}",
      "curveMode": 4,
      "curveTo": "{0.14285714285714285, 0}",
      "hasCurveFrom": true,
      "hasCurveTo": false,
      "point": "{0.14285714285714285, 0}"
    },
    {
      "_class": "curvePoint",
      "cornerRadius": 0,
      "curveFrom": "{0, 0.22727272727272727}",
      "curveMode": 4,
      "curveTo": "{0, 0.10227272727272728}",
      "hasCurveFrom": false,
      "hasCurveTo": true,
      "point": "{0, 0.22727272727272727}"
    },
    {
      "_class": "curvePoint",
      "cornerRadius": 0,
      "curveFrom": "{0, 1}",
      "curveMode": 1,
      "curveTo": "{0, 1}",
      "hasCurveFrom": false,
      "hasCurveTo": false,
      "point": "{0, 1}"
    }
  ],
  "resizingConstraint": 63,
  "resizingType": 0,
  "rotation": 0,
  "shouldBreakMaskChain": false
}