{
  "_class": "shapeGroup",
  "booleanOperation": 0,
  "clippingMaskMode": 0,
  "do_objectID": "F526CE0B-0258-4EEA-98AC-C41BC17A591F",
  "exportOptions": {
    "_class": "exportOptions",
    "do_objectID": "CDBAC254-30A1-4531-9347-DDDAA2319932",
    "exportFormats": [
    ],
    "includedLayerIds": [
    ],
    "layerOptions": 0,
    "shouldTrim": false
  },
  "frame": {
    "_class": "rect",
    "constrainProportions": false,
    "do_objectID": "B9DF1CBC-3E7E-4557-A9DD-901DD98C9871",
    "height": 28.23529411764706,
    "width": 28.75,
    "x": 0,
    "y": 0
  },
  "hasClickThrough": false,
  "hasClippingMask": false,
  "isFixedToViewport": false,
  "isFlippedHorizontal": false,
  "isFlippedVertical": false,
  "isLocked": false,
  "isVisible": true,
  "layerListExpandedType": 1,
  "layers": [
    {
      "class": "shapePath",
      "id": "4949C7DC-F4A3-45E5-92C0-2925B6389ECF"
    },
    {
      "class": "shapePath",
      "id": "76B94150-5BC8-43E1-88F5-DF7D90E34415"
    },
    {
      "class": "shapePath",
      "id": "E5831903-6869-4DF4-9F47-E83CF8D87800"
    },
    {
      "class": "shapePath",
      "id": "B986576C-40C8-4CA0-AF2F-5F9B9867720F"
    }
  ],
  "name": "Shape",
  "nameIsFixed": false,
  "resizingConstraint": 63,
  "resizingType": 0,
  "rotation": 0,
  "shouldBreakMaskChain": false,
  "style": {
    "_class": "style",
    "do_objectID": "5B775370-18BC-4C83-BB4D-FAF1FE3BC2B2",
    "endMarkerType": 0,
    "fills": [
      {
        "_class": "fill",
        "color": {
          "_class": "color",
          "alpha": 1,
          "blue": 1,
          "green": 1,
          "red": 1
        },
        "fillType": 0,
        "isEnabled": true,
        "noiseIndex": 0,
        "noiseIntensity": 0,
        "patternFillType": 1,
        "patternTileScale": 1
      }
    ],
    "miterLimit": 10,
    "startMarkerType": 0,
    "windingRule": 0
  },
  "windingRule": 0
}