{
  "_class": "shapeGroup",
  "booleanOperation": 0,
  "clippingMaskMode": 0,
  "do_objectID": "A2A8A7A3-2DE1-43C1-A6E3-BE956416E618",
  "exportOptions": {
    "_class": "exportOptions",
    "do_objectID": "428DF1C4-6EE5-4EA6-927B-AE0A1503E750",
    "exportFormats": [
    ],
    "includedLayerIds": [
    ],
    "layerOptions": 0,
    "shouldTrim": false
  },
  "frame": {
    "_class": "rect",
    "constrainProportions": false,
    "do_objectID": "1534432D-7D8F-4BB3-9343-FDA7C001F17E",
    "height": 9.51549865229115,
    "width": 9.71337667454691,
    "x": 15.19934338061466,
    "y": 0.05864555256064623
  },
  "hasClickThrough": false,
  "hasClippingMask": false,
  "isFixedToViewport": false,
  "isFlippedHorizontal": false,
  "isFlippedVertical": false,
  "isLocked": false,
  "isVisible": true,
  "layerListExpandedType": 1,
  "layers": [
    {
      "class": "shapePath",
      "id": "78C4179A-0647-41F7-AE74-468621DB4A18"
    }
  ],
  "name": "Shape",
  "nameIsFixed": false,
  "resizingConstraint": 63,
  "resizingType": 0,
  "rotation": 0,
  "shouldBreakMaskChain": false,
  "style": {
    "_class": "style",
    "blur": {
      "_class": "blur",
      "center": "{0.5, 0.5}",
      "do_objectID": "39BFB03D-72AB-4B52-837C-59A144D4582C",
      "isEnabled": false,
      "motionAngle": 0,
      "radius": 20,
      "type": 0
    },
    "do_objectID": "B2096E5E-73E0-4F3A-BE09-295BFC6FBEA0",
    "endMarkerType": 0,
    "fills": [
      {
        "_class": "fill",
        "color": {
          "_class": "color",
          "alpha": 1,
          "blue": 0.3450980392156863,
          "green": 0.4392156862745098,
          "red": 1
        },
        "fillType": 0,
        "isEnabled": true,
        "noiseIndex": 0,
        "noiseIntensity": 0,
        "patternFillType": 1,
        "patternTileScale": 1
      }
    ],
    "miterLimit": 10,
    "startMarkerType": 0,
    "windingRule": 0
  },
  "windingRule": 0
}