{
  "_class": "bitmap",
  "booleanOperation": 0,
  "clippingMask": "{{0, 0}, {1, 1}}",
  "do_objectID": "E8220CDD-75DD-4578-9AFF-92E0532DB3B3",
  "exportOptions": {
    "_class": "exportOptions",
    "do_objectID": "A4CC6E01-4C9C-4B7C-A202-58870773D019",
    "exportFormats": [
    ],
    "includedLayerIds": [
    ],
    "layerOptions": 0,
    "shouldTrim": false
  },
  "fillReplacesImage": false,
  "frame": {
    "_class": "rect",
    "constrainProportions": true,
    "do_objectID": "3146FDCD-8B95-4991-9E58-9812E32F498C",
    "height": 96,
    "width": 136,
    "x": -36,
    "y": 0
  },
  "image": {
    "_class": "MSJSONFileReference",
    "_ref": "images/5ee629e9b47be759129b7328dedaf9e1c49a8069.png",
    "_ref_class": "MSImageData"
  },
  "intendedDPI": 72,
  "isFixedToViewport": false,
  "isFlippedHorizontal": false,
  "isFlippedVertical": false,
  "isLocked": false,
  "isVisible": true,
  "layerListExpandedType": 0,
  "name": "Bitmap",
  "nameIsFixed": false,
  "resizingConstraint": 63,
  "resizingType": 0,
  "rotation": 0,
  "shouldBreakMaskChain": false,
  "style": {
    "_class": "style",
    "do_objectID": "97E8867D-A3ED-4B7F-BE61-750D17AA6FDE",
    "endMarkerType": 0,
    "miterLimit": 10,
    "startMarkerType": 0,
    "windingRule": 1
  }
}