{
  "_class": "shapeGroup",
  "booleanOperation": 0,
  "clippingMaskMode": 0,
  "do_objectID": "EF3366C4-7DD7-430B-9CF9-F588C0A2F406",
  "exportOptions": {
    "_class": "exportOptions",
    "do_objectID": "6D1B6283-B051-41A1-8838-B81FEA9AA8B3",
    "exportFormats": [
    ],
    "includedLayerIds": [
    ],
    "layerOptions": 0,
    "shouldTrim": false
  },
  "frame": {
    "_class": "rect",
    "constrainProportions": false,
    "do_objectID": "30F8EDE6-E5EA-4B37-846B-51671796F331",
    "height": 12.54873646209382,
    "width": 10.84731738849387,
    "x": 11.1327731092437,
    "y": 0
  },
  "hasClickThrough": false,
  "hasClippingMask": false,
  "isFixedToViewport": false,
  "isFlippedHorizontal": false,
  "isFlippedVertical": false,
  "isLocked": false,
  "isVisible": true,
  "layerListExpandedType": 1,
  "layers": [
    {
      "class": "shapePath",
      "id": "F208FB5F-54FA-4F14-8CE9-CC02A0CDC137"
    }
  ],
  "name": "Shape",
  "nameIsFixed": false,
  "resizingConstraint": 63,
  "resizingType": 0,
  "rotation": 0,
  "shouldBreakMaskChain": false,
  "style": {
    "_class": "style",
    "do_objectID": "581A3EF7-54C0-4B77-A12E-942279722788",
    "endMarkerType": 0,
    "fills": [
      {
        "_class": "fill",
        "color": {
          "_class": "color",
          "alpha": 1,
          "blue": 0.9294117647058824,
          "green": 0.9294117647058824,
          "red": 0.9294117647058824
        },
        "fillType": 0,
        "isEnabled": true,
        "noiseIndex": 0,
        "noiseIntensity": 0,
        "patternFillType": 1,
        "patternTileScale": 1
      }
    ],
    "miterLimit": 10,
    "startMarkerType": 0,
    "windingRule": 0
  },
  "windingRule": 0
}